README.rst
setup.py
src/pygraph_redis/__init__.py
src/pygraph_redis/directed_graph.py
src/pygraph_redis.egg-info/PKG-INFO
src/pygraph_redis.egg-info/SOURCES.txt
src/pygraph_redis.egg-info/dependency_links.txt
src/pygraph_redis.egg-info/requires.txt
src/pygraph_redis.egg-info/top_level.txt