Metadata-Version: 1.1
Name: pygraph-redis
Version: 0.2.1
Summary: Python Library to manipulate directed graphs in redis
Home-page: https://github.com/kakwa/pygraph_redis
Author: Pierre-Francois Carpentier
Author-email: carpentier.pf@gmail.com
License: Copyright (c) 2013 Pierre-Francois Carpentier <carpentier.pf@gmail.com> 
